pro_craft_infer/__init__.py
pro_craft_infer/core.py
pro_craft_infer/database.py
pro_craft_infer/evals.py
pro_craft_infer/log_router.py
pro_craft_infer/utils.py
pro_craft_infer-0.1.17.dist-info/METADATA
pro_craft_infer-0.1.17.dist-info/WHEEL
pro_craft_infer-0.1.17.dist-info/top_level.txt
pro_craft_infer-0.1.17.dist-info/RECORD
