Metadata-Version: 2.4
Name: pro-craft-infer
Version: 0.1.17
Summary: Add your description here
Requires-Python: >=3.12
Requires-Dist: aiomysql>=0.3.2
Requires-Dist: anyio>=4.11.0
Requires-Dist: fastapi>=0.119.1
Requires-Dist: greenlet>=3.2.4
Requires-Dist: modusched>=1.0.2
Requires-Dist: sqlalchemy>=2.0.44
Requires-Dist: toml>=0.10.2
Requires-Dist: toon-format
Requires-Dist: uvicorn>=0.38.0
